{
  "objectInfo" : {
    "id" : "0zZxGLb3CYMhZMBbxvzgi5",
    "name" : "cdi_tkf_flow_acx_coverage_item_bronze_load_daily",
    "type" : "TASKFLOW",
    "metadata" : {
      "modelVersion" : {
        "major" : 1,
        "minor" : 0
      },
      "repoInfo" : {
        "repoHandle" : "HH0thJ6gaabclvA-gt-43224372-2026-01-22T03:38:17.534Z::tf.xml"
      },
      "contextAttributes" : null,
      "additionalInfo" : {
        "description" : "",
        "contentType" : "application/json; charset=utf-8",
        "documentState" : "VALID"
      }
    }
  },
  "dataFileExtension" : "xml",
  "updateTime" : "2026-01-30T22:28:12.943Z",
  "objectRefs" : [ {
    "id" : "4cpY7DCUyitlvzGvfzJ4qD",
    "name" : "cdi_tsk_map_acx_coverage_item_bronze_load",
    "type" : "MTT",
    "metadata" : {
      "modelVersion" : {
        "major" : 0,
        "minor" : 0
      },
      "repoInfo" : {
        "repoHandle" : "01COEW0Z0000000002DJ"
      },
      "contextAttributes" : [ {
        "name" : "id",
        "value" : "@1"
      } ],
      "additionalInfo" : {
        "description" : null,
        "contentType" : "JSON",
        "documentState" : "VALID"
      }
    },
    "path" : "/Explore/Andover_Rehana/ACX"
  }, {
    "id" : "7UKmFxEZXOoc9CPttoMt6g",
    "name" : "cdi_tsk_map_batch_load_ACX",
    "type" : "MTT",
    "metadata" : {
      "modelVersion" : {
        "major" : 0,
        "minor" : 0
      },
      "repoInfo" : {
        "repoHandle" : "01COEW0Z00000000020L"
      },
      "contextAttributes" : null,
      "additionalInfo" : {
        "description" : null,
        "contentType" : "JSON",
        "documentState" : "VALID"
      }
    },
    "path" : "/Explore/cdi_project_operational"
  }, {
    "id" : "aLMwejscOtmd9Til6Sn10c",
    "name" : "cdi_tsk_map_batch_load_status_update_ACX",
    "type" : "MTT",
    "metadata" : {
      "modelVersion" : {
        "major" : 0,
        "minor" : 0
      },
      "repoInfo" : {
        "repoHandle" : "01COEW0Z00000000020R"
      },
      "contextAttributes" : null,
      "additionalInfo" : {
        "description" : null,
        "contentType" : "JSON",
        "documentState" : "VALID"
      }
    },
    "path" : "/Explore/cdi_project_operational"
  } ],
  "readableFileExtension" : null,
  "readableFilePresent" : false
}