{
  "objectInfo" : {
    "id" : "9DEJ6NCjmYnhmlv54JAr2E",
    "name" : "m_load_import_NonPremTrans_from_file",
    "type" : "DTEMPLATE",
    "metadata" : {
      "modelVersion" : {
        "major" : 0,
        "minor" : 0
      },
      "repoInfo" : {
        "repoHandle" : "01COEW170000000000C1"
      },
      "contextAttributes" : [ {
        "name" : "id",
        "value" : "@1"
      } ],
      "additionalInfo" : {
        "description" : "This mapping will load data from the nonpremium transaction files into the import layer table.",
        "contentType" : "JSON",
        "documentState" : "VALID"
      }
    }
  },
  "dataFileExtension" : "zip",
  "updateTime" : "2024-02-12T17:55:08.663Z",
  "objectRefs" : [ {
    "id" : "hDaDl41RzkCfVBbYB4kTEC",
    "name" : "FW_m_load_import_NonPremTrans_from_fileSQ_NonPremTrans",
    "type" : "FWCONFIG",
    "metadata" : {
      "modelVersion" : {
        "major" : 0,
        "minor" : 0
      },
      "repoInfo" : {
        "repoHandle" : "01COEW29000000000003"
      },
      "contextAttributes" : [ {
        "name" : "id",
        "value" : "@1"
      } ],
      "additionalInfo" : {
        "description" : "",
        "contentType" : "JSON",
        "documentState" : "VALID"
      }
    },
    "path" : "/Explore/Andover_Extra/wf_Load_NonPremTrans"
  } ]
}