<aetgt:getResponse xmlns:aetgt="http://schemas.active-endpoints.com/appmodules/repository/2010/10/avrepository.xsd"
                   xmlns:types1="http://schemas.active-endpoints.com/appmodules/repository/2010/10/avrepository.xsd">
   <types1:Item>
      <types1:EntryId>f3fZPE4zlrMZgpD-gt-10424113-2023-11-22T16:34:00.509Z::tf.xml</types1:EntryId>
      <types1:Name>wf_m_Load_StatelineCedPaidLossHistory</types1:Name>
      <types1:MimeType>application/xml+taskflow</types1:MimeType>
      <types1:Description>Workflow generated by PC2Cloud : wf_m_Load_StatelineCedPaidLossHistory</types1:Description>
      <types1:AppliesTo/>
      <types1:Tags/>
      <types1:VersionLabel>1.0</types1:VersionLabel>
      <types1:State>CURRENT</types1:State>
      <types1:ProcessGroup/>
      <types1:CreatedBy>bfirtin@andovercos.com</types1:CreatedBy>
      <types1:CreationDate>2023-11-22T16:34:01Z</types1:CreationDate>
      <types1:ModifiedBy>akumar@andovercos.com</types1:ModifiedBy>
      <types1:ModificationDate>2023-12-22T17:03:08Z</types1:ModificationDate>
      <types1:PublicationStatus>published</types1:PublicationStatus>
      <types1:PublishedBy>akumar@andovercos.com</types1:PublishedBy>
      <types1:PublicationDate>2023-12-22T17:03:12Z</types1:PublicationDate>
      <types1:PublishedContributionId>project:/tf.wf_m_Load_StatelineCedPaidLossHistory/wf_m_Load_StatelineCedPaidLossHistory.tf.xml</types1:PublishedContributionId>
      <types1:AutosaveExists>false</types1:AutosaveExists>
      <types1:Entry>
         <taskflow xmlns="http://schemas.active-endpoints.com/appmodules/screenflow/2010/10/avosScreenflow.xsd"
                   xmlns:tfm="http://schemas.active-endpoints.com/appmodules/screenflow/2021/04/taskflowModel.xsd"
                   xmlns:list="urn:activevos:spi:list:functions"
                   displayName="wf_m_Load_StatelineCedPaidLossHistory"
                   name="wf_m_Load_StatelineCedPaidLossHistory"
                   overrideAPIName="true">
            <parameterSet xmlns="http://schemas.active-endpoints.com/appmodules/screenflow/2021/04/taskflowModel.xsd"/>
            <appliesTo/>
            <description>Workflow generated by PC2Cloud : wf_m_Load_StatelineCedPaidLossHistory</description>
            <tags/>
            <generator>Informatica Process Designer 11</generator>
            <input>
               <parameter description=""
                          name="InputMappingTaskParameterFileDir"
                          type="string">
                  <options>
                     <option name="required">false</option>
                  </options>
               </parameter>
               <parameter description=""
                          name="InputMappingTaskParameterFileName"
                          type="string">
                  <options>
                     <option name="required">false</option>
                  </options>
               </parameter>
            </input>
            <tempFields>
               <field description=""
                      name="s_m_Load_CededLossOs_From_File"
                      type="reference">
                  <options>
                     <option name="failOnNotRun">false</option>
                     <option name="failOnFault">false</option>
                     <option name="referenceTo">$po:s-m-Load-CededLossOs-From-File</option>
                     <option name="required">false</option>
                     <option name="isCopy">true</option>
                  </options>
               </field>
               <field description=""
                      name="s_m_Load_PMS_Ceded_Loss_Reserves_PMS"
                      type="reference">
                  <options>
                     <option name="failOnNotRun">false</option>
                     <option name="failOnFault">false</option>
                     <option name="referenceTo">$po:s-m-Load-PMS-Ceded-Loss-Reserves-PMS</option>
                     <option name="required">false</option>
                     <option name="isCopy">true</option>
                  </options>
               </field>
               <field description=""
                      name="s_m_Load_Ceded_LossReinsurance_Stg"
                      type="reference">
                  <options>
                     <option name="failOnNotRun">false</option>
                     <option name="failOnFault">true</option>
                     <option name="referenceTo">$po:s-m-Load-Ceded-LossReinsurance-Stg</option>
                     <option name="required">false</option>
                     <option name="isCopy">true</option>
                  </options>
               </field>
               <field description=""
                      name="s_m_Ceded_PMSFactLoss_ReinsuranceTransaction"
                      type="reference">
                  <options>
                     <option name="failOnNotRun">false</option>
                     <option name="failOnFault">true</option>
                     <option name="referenceTo">$po:s-m-Ceded-PMSFactLoss-ReinsuranceTransaction</option>
                     <option name="required">false</option>
                     <option name="isCopy">true</option>
                  </options>
               </field>
               <field description="" name="PMBadFileDir" type="string">
                  <options>
                     <option name="required">false</option>
                  </options>
               </field>
               <field description="" name="PMCacheDir" type="string">
                  <options>
                     <option name="required">false</option>
                  </options>
               </field>
               <field description="" name="PMExtProcDir" type="string">
                  <options>
                     <option name="required">false</option>
                  </options>
               </field>
               <field description="" name="PMFailureEmailUser" type="string">
                  <options>
                     <option name="required">false</option>
                  </options>
               </field>
               <field description="" name="PMFolderName" type="string">
                  <options>
                     <option name="required">false</option>
                     <option name="initialvalue">util:getAssetLocation()</option>
                  </options>
               </field>
               <field description="" name="PMIntegrationServiceName" type="string">
                  <options>
                     <option name="required">false</option>
                  </options>
               </field>
               <field description="" name="PMLookupFileDir" type="string">
                  <options>
                     <option name="required">false</option>
                  </options>
               </field>
               <field description="" name="PMRepositoryServiceName" type="string">
                  <options>
                     <option name="required">false</option>
                  </options>
               </field>
               <field description="" name="PMRepositoryUserName" type="string">
                  <options>
                     <option name="required">false</option>
                     <option name="initialvalue">util:getUserName()</option>
                  </options>
               </field>
               <field description="" name="PMRootDir" type="string">
                  <options>
                     <option name="required">false</option>
                  </options>
               </field>
               <field description="" name="PMSessionLogDir" type="string">
                  <options>
                     <option name="required">false</option>
                  </options>
               </field>
               <field description="" name="PMSourceFileDir" type="string">
                  <options>
                     <option name="required">false</option>
                  </options>
               </field>
               <field description="" name="PMStorageDir" type="string">
                  <options>
                     <option name="required">false</option>
                  </options>
               </field>
               <field description="" name="PMSuccessEmailUser" type="string">
                  <options>
                     <option name="required">false</option>
                  </options>
               </field>
               <field description="" name="PMTargetFileDir" type="string">
                  <options>
                     <option name="required">false</option>
                  </options>
               </field>
               <field description="" name="PMTempDir" type="string">
                  <options>
                     <option name="required">false</option>
                  </options>
               </field>
               <field description="" name="PMWorkflowLogDir" type="string">
                  <options>
                     <option name="required">false</option>
                  </options>
               </field>
               <field description="" name="PMWorkflowName" type="string">
                  <options>
                     <option name="required">false</option>
                     <option name="initialvalue">util:getAssetName()</option>
                  </options>
               </field>
               <field description="" name="PMWorkflowRunId" type="int">
                  <options>
                     <option name="required">false</option>
                     <option name="initialvalue">util:getProcessId()</option>
                  </options>
               </field>
               <field description="" name="PMWorkflowRunInstanceName" type="string">
                  <options>
                     <option name="required">false</option>
                  </options>
               </field>
               <field description="" name="SYSDATE" type="datetime">
                  <options>
                     <option name="required">false</option>
                     <option name="initialvalue">fn:current-date()</option>
                  </options>
               </field>
               <field description="" name="WORKFLOWSTARTTIME" type="datetime">
                  <options>
                     <option name="required">false</option>
                     <option name="initialvalue">util:getInstanceStartTime()</option>
                  </options>
               </field>
            </tempFields>
            <notes/>
            <deployment skipIfRunning="false" suspendOnFault="false" tracingLevel="verbose">
               <rest>
                  <allowedGroups>
                     <group>Informatica-SQL</group>
                  </allowedGroups>
               </rest>
            </deployment>
            <flow id="a">
               <start id="b">
                  <title>Start</title>
                  <link id="loornygt" targetId="loornygr"/>
               </start>
               <assignment id="loornygr">
                  <title>Assignment_PC_Variables</title>
                  <operation source="constant" to="temp.PMBadFileDir"/>
                  <operation source="constant" to="temp.PMCacheDir"/>
                  <operation source="constant" to="temp.PMExtProcDir"/>
                  <operation source="constant" to="temp.PMFailureEmailUser"/>
                  <operation source="formula" to="temp.PMFolderName">
                     <expression language="XQuery">util:getAssetLocation()</expression>
                  </operation>
                  <operation source="constant" to="temp.PMIntegrationServiceName"/>
                  <operation source="constant" to="temp.PMLookupFileDir"/>
                  <operation source="constant" to="temp.PMRepositoryServiceName"/>
                  <operation source="formula" to="temp.PMRepositoryUserName">
                     <expression language="XQuery">util:getUserName()</expression>
                  </operation>
                  <operation source="constant" to="temp.PMRootDir"/>
                  <operation source="constant" to="temp.PMSessionLogDir"/>
                  <operation source="constant" to="temp.PMSourceFileDir"/>
                  <operation source="constant" to="temp.PMStorageDir"/>
                  <operation source="constant" to="temp.PMSuccessEmailUser"/>
                  <operation source="constant" to="temp.PMTargetFileDir"/>
                  <operation source="constant" to="temp.PMTempDir"/>
                  <operation source="constant" to="temp.PMWorkflowLogDir"/>
                  <operation source="formula" to="temp.PMWorkflowName">
                     <expression language="XQuery">util:getAssetName()</expression>
                  </operation>
                  <operation source="formula" to="temp.PMWorkflowRunId">
                     <expression language="XQuery">util:getProcessId()</expression>
                  </operation>
                  <operation source="constant" to="temp.PMWorkflowRunInstanceName"/>
                  <operation source="formula" to="temp.SYSDATE">
                     <expression language="XQuery">fn:current-date()</expression>
                  </operation>
                  <operation source="formula" to="temp.WORKFLOWSTARTTIME">
                     <expression language="XQuery">util:getInstanceStartTime()</expression>
                  </operation>
                  <link id="loornygu" targetId="loornygq"/>
               </assignment>
               <assignment id="loornygq">
                  <title>Assignment_PC_Workflow_Parameter_File</title>
                  <operation source="formula" to="input.InputMappingTaskParameterFileDir">
                     <expression language="XQuery">if (fn:empty($input.InputMappingTaskParameterFileDir)) then 'D:\app\Informatica\server\infa_shared\PrmFiles\' else $input.InputMappingTaskParameterFileDir</expression>
                  </operation>
                  <operation source="formula" to="input.InputMappingTaskParameterFileName">
                     <expression language="XQuery">if (fn:empty($input.InputMappingTaskParameterFileName)) then 'Andover_Parm_GW.txt' else $input.InputMappingTaskParameterFileName</expression>
                  </operation>
                  <link id="loornygv" targetId="loornygh"/>
               </assignment>
               <eventContainer id="loornygh">
                  <service id="loornygi">
                     <title>s_m_Load_Ceded_LossReinsurance_Stg</title>
                     <serviceName>ICSExecuteDataTask</serviceName>
                     <serviceGUID/>
                     <serviceInput>
                        <parameter name="Task Name" source="constant" updatable="true">s_m_Load_Ceded_LossReinsurance_Stg</parameter>
                        <parameter name="Wait for Task to Complete" source="constant" updatable="true">true</parameter>
                        <parameter name="Max Wait" source="constant" updatable="true">604800</parameter>
                        <parameter name="GUID" source="constant" updatable="true">5I11RN9wcCyh84albp4p6T</parameter>
                        <parameter name="Has Inout Parameters" source="constant" updatable="true">false</parameter>
                        <parameter name="Task Type" source="constant" updatable="true">MCT</parameter>
                        <parameter name="taskField" source="nested">
                           <operation source="field" to="s-m-Load-Ceded-LossReinsurance-Stg">temp.s_m_Load_Ceded_LossReinsurance_Stg</operation>
                        </parameter>
                     </serviceInput>
                     <serviceOutput>
                        <operation source="field"
                                   to="temp.s_m_Load_Ceded_LossReinsurance_Stg/output/Object_Name">Object Name</operation>
                        <operation source="field"
                                   to="temp.s_m_Load_Ceded_LossReinsurance_Stg/output/Run_Id">Run Id</operation>
                        <operation source="field"
                                   to="temp.s_m_Load_Ceded_LossReinsurance_Stg/output/Log_Id">Log Id</operation>
                        <operation source="field"
                                   to="temp.s_m_Load_Ceded_LossReinsurance_Stg/output/Task_Id">Task Id</operation>
                        <operation source="field"
                                   to="temp.s_m_Load_Ceded_LossReinsurance_Stg/output/Task_Status">Task Status</operation>
                        <operation source="field"
                                   to="temp.s_m_Load_Ceded_LossReinsurance_Stg/output/Success_Source_Rows">Success Source Rows</operation>
                        <operation source="field"
                                   to="temp.s_m_Load_Ceded_LossReinsurance_Stg/output/Failed_Source_Rows">Failed Source Rows</operation>
                        <operation source="field"
                                   to="temp.s_m_Load_Ceded_LossReinsurance_Stg/output/Success_Target_Rows">Success Target Rows</operation>
                        <operation source="field"
                                   to="temp.s_m_Load_Ceded_LossReinsurance_Stg/output/Failed_Target_Rows">Failed Target Rows</operation>
                        <operation source="field"
                                   to="temp.s_m_Load_Ceded_LossReinsurance_Stg/output/Start_Time">Start Time</operation>
                        <operation source="field"
                                   to="temp.s_m_Load_Ceded_LossReinsurance_Stg/output/End_Time">End Time</operation>
                        <operation source="field"
                                   to="temp.s_m_Load_Ceded_LossReinsurance_Stg/output/Error_Message">Error Message</operation>
                        <operation source="field"
                                   to="temp.s_m_Load_Ceded_LossReinsurance_Stg/output/TotalTransErrors">Total Transformation Errors</operation>
                        <operation source="field"
                                   to="temp.s_m_Load_Ceded_LossReinsurance_Stg/output/FirstErrorCode">First Error Code</operation>
                     </serviceOutput>
                  </service>
                  <link id="loornyh4" targetId="loornygx"/>
                  <events>
                     <catch faultField="temp.s_m_Load_Ceded_LossReinsurance_Stg/fault"
                            id="loornygj"
                            interrupting="true"
                            name="error"/>
                     <catch faultField="temp.s_m_Load_Ceded_LossReinsurance_Stg/fault"
                            id="loornygk"
                            interrupting="true"
                            name="warning"/>
                  </events>
               </eventContainer>
               <container id="loornygx" type="exclusive">
                  <title>Link_Condition_loornygw</title>
                  <flow id="loornygz">
                     <eventContainer id="loornygl">
                        <service id="loornygm">
                           <title>s_m_Ceded_PMSFactLoss_ReinsuranceTransaction</title>
                           <serviceName>ICSExecuteDataTask</serviceName>
                           <serviceGUID/>
                           <serviceInput>
                              <parameter name="Task Name" source="constant" updatable="true">s_m_Ceded_PMSFactLoss_ReinsuranceTransaction</parameter>
                              <parameter name="Wait for Task to Complete" source="constant" updatable="true">true</parameter>
                              <parameter name="Max Wait" source="constant" updatable="true">604800</parameter>
                              <parameter name="GUID" source="constant" updatable="true">31o9QITvcR9bDYrM3VArmh</parameter>
                              <parameter name="Has Inout Parameters" source="constant" updatable="true">false</parameter>
                              <parameter name="Task Type" source="constant" updatable="true">MCT</parameter>
                              <parameter name="taskField" source="nested">
                                 <operation source="field" to="s-m-Ceded-PMSFactLoss-ReinsuranceTransaction">temp.s_m_Ceded_PMSFactLoss_ReinsuranceTransaction</operation>
                              </parameter>
                           </serviceInput>
                           <serviceOutput>
                              <operation source="field"
                                         to="temp.s_m_Ceded_PMSFactLoss_ReinsuranceTransaction/output/Object_Name">Object Name</operation>
                              <operation source="field"
                                         to="temp.s_m_Ceded_PMSFactLoss_ReinsuranceTransaction/output/Run_Id">Run Id</operation>
                              <operation source="field"
                                         to="temp.s_m_Ceded_PMSFactLoss_ReinsuranceTransaction/output/Log_Id">Log Id</operation>
                              <operation source="field"
                                         to="temp.s_m_Ceded_PMSFactLoss_ReinsuranceTransaction/output/Task_Id">Task Id</operation>
                              <operation source="field"
                                         to="temp.s_m_Ceded_PMSFactLoss_ReinsuranceTransaction/output/Task_Status">Task Status</operation>
                              <operation source="field"
                                         to="temp.s_m_Ceded_PMSFactLoss_ReinsuranceTransaction/output/Success_Source_Rows">Success Source Rows</operation>
                              <operation source="field"
                                         to="temp.s_m_Ceded_PMSFactLoss_ReinsuranceTransaction/output/Failed_Source_Rows">Failed Source Rows</operation>
                              <operation source="field"
                                         to="temp.s_m_Ceded_PMSFactLoss_ReinsuranceTransaction/output/Success_Target_Rows">Success Target Rows</operation>
                              <operation source="field"
                                         to="temp.s_m_Ceded_PMSFactLoss_ReinsuranceTransaction/output/Failed_Target_Rows">Failed Target Rows</operation>
                              <operation source="field"
                                         to="temp.s_m_Ceded_PMSFactLoss_ReinsuranceTransaction/output/Start_Time">Start Time</operation>
                              <operation source="field"
                                         to="temp.s_m_Ceded_PMSFactLoss_ReinsuranceTransaction/output/End_Time">End Time</operation>
                              <operation source="field"
                                         to="temp.s_m_Ceded_PMSFactLoss_ReinsuranceTransaction/output/Error_Message">Error Message</operation>
                              <operation source="field"
                                         to="temp.s_m_Ceded_PMSFactLoss_ReinsuranceTransaction/output/TotalTransErrors">Total Transformation Errors</operation>
                              <operation source="field"
                                         to="temp.s_m_Ceded_PMSFactLoss_ReinsuranceTransaction/output/FirstErrorCode">First Error Code</operation>
                           </serviceOutput>
                        </service>
                        <link id="loornyhd" targetId="loornyh6"/>
                        <events>
                           <catch faultField="temp.s_m_Ceded_PMSFactLoss_ReinsuranceTransaction/fault"
                                  id="loornygn"
                                  interrupting="true"
                                  name="error"/>
                           <catch faultField="temp.s_m_Ceded_PMSFactLoss_ReinsuranceTransaction/fault"
                                  id="loornygo"
                                  interrupting="true"
                                  name="warning"/>
                        </events>
                     </eventContainer>
                     <container id="loornyh6" type="exclusive">
                        <title>Link_Condition_loornyh5</title>
                        <flow id="loornyh8">
                           <eventContainer id="loornyg9">
                              <service id="loornyga">
                                 <title>s_m_Load_CededLossOs_From_File</title>
                                 <serviceName>ICSExecuteDataTask</serviceName>
                                 <serviceGUID/>
                                 <serviceInput>
                                    <parameter name="Task Name" source="constant" updatable="true">s_m_Load_CededLossOs_From_File</parameter>
                                    <parameter name="Wait for Task to Complete" source="constant" updatable="true">true</parameter>
                                    <parameter name="Max Wait" source="constant" updatable="true">604800</parameter>
                                    <parameter name="GUID" source="constant" updatable="true">dvEbO2pauQ8kL5pUhD3ZI1</parameter>
                                    <parameter name="Has Inout Parameters" source="constant" updatable="true">false</parameter>
                                    <parameter name="Task Type" source="constant" updatable="true">MCT</parameter>
                                    <parameter name="taskField" source="nested">
                                       <operation source="field" to="s-m-Load-CededLossOs-From-File">temp.s_m_Load_CededLossOs_From_File</operation>
                                    </parameter>
                                 </serviceInput>
                                 <serviceOutput>
                                    <operation source="field"
                                               to="temp.s_m_Load_CededLossOs_From_File/output/Object_Name">Object Name</operation>
                                    <operation source="field" to="temp.s_m_Load_CededLossOs_From_File/output/Run_Id">Run Id</operation>
                                    <operation source="field" to="temp.s_m_Load_CededLossOs_From_File/output/Log_Id">Log Id</operation>
                                    <operation source="field" to="temp.s_m_Load_CededLossOs_From_File/output/Task_Id">Task Id</operation>
                                    <operation source="field"
                                               to="temp.s_m_Load_CededLossOs_From_File/output/Task_Status">Task Status</operation>
                                    <operation source="field"
                                               to="temp.s_m_Load_CededLossOs_From_File/output/Success_Source_Rows">Success Source Rows</operation>
                                    <operation source="field"
                                               to="temp.s_m_Load_CededLossOs_From_File/output/Failed_Source_Rows">Failed Source Rows</operation>
                                    <operation source="field"
                                               to="temp.s_m_Load_CededLossOs_From_File/output/Success_Target_Rows">Success Target Rows</operation>
                                    <operation source="field"
                                               to="temp.s_m_Load_CededLossOs_From_File/output/Failed_Target_Rows">Failed Target Rows</operation>
                                    <operation source="field"
                                               to="temp.s_m_Load_CededLossOs_From_File/output/Start_Time">Start Time</operation>
                                    <operation source="field" to="temp.s_m_Load_CededLossOs_From_File/output/End_Time">End Time</operation>
                                    <operation source="field"
                                               to="temp.s_m_Load_CededLossOs_From_File/output/Error_Message">Error Message</operation>
                                    <operation source="field"
                                               to="temp.s_m_Load_CededLossOs_From_File/output/TotalTransErrors">Total Transformation Errors</operation>
                                    <operation source="field"
                                               to="temp.s_m_Load_CededLossOs_From_File/output/FirstErrorCode">First Error Code</operation>
                                 </serviceOutput>
                              </service>
                              <link id="loornyhm" targetId="loornyhf"/>
                              <events>
                                 <catch faultField="temp.s_m_Load_CededLossOs_From_File/fault"
                                        id="loornygb"
                                        interrupting="true"
                                        name="error"/>
                                 <catch faultField="temp.s_m_Load_CededLossOs_From_File/fault"
                                        id="loornygc"
                                        interrupting="true"
                                        name="warning"/>
                              </events>
                           </eventContainer>
                           <container id="loornyhf" type="exclusive">
                              <title>Link_Condition_loornyhe</title>
                              <flow id="loornyhh">
                                 <eventContainer id="loornygd">
                                    <service id="loornyge">
                                       <title>s_m_Load_PMS_Ceded_Loss_Reserves_PMS</title>
                                       <serviceName>ICSExecuteDataTask</serviceName>
                                       <serviceGUID/>
                                       <serviceInput>
                                          <parameter name="Task Name" source="constant" updatable="true">s_m_Load_PMS_Ceded_Loss_Reserves_PMS</parameter>
                                          <parameter name="Wait for Task to Complete" source="constant" updatable="true">true</parameter>
                                          <parameter name="Max Wait" source="constant" updatable="true">604800</parameter>
                                          <parameter name="GUID" source="constant" updatable="true">kmNAF8txEohkUNejeuuWIh</parameter>
                                          <parameter name="Has Inout Parameters" source="constant" updatable="true">false</parameter>
                                          <parameter name="Task Type" source="constant" updatable="true">MCT</parameter>
                                          <parameter name="taskField" source="nested">
                                             <operation source="field" to="s-m-Load-PMS-Ceded-Loss-Reserves-PMS">temp.s_m_Load_PMS_Ceded_Loss_Reserves_PMS</operation>
                                          </parameter>
                                       </serviceInput>
                                       <serviceOutput>
                                          <operation source="field"
                                                     to="temp.s_m_Load_PMS_Ceded_Loss_Reserves_PMS/output/Object_Name">Object Name</operation>
                                          <operation source="field"
                                                     to="temp.s_m_Load_PMS_Ceded_Loss_Reserves_PMS/output/Run_Id">Run Id</operation>
                                          <operation source="field"
                                                     to="temp.s_m_Load_PMS_Ceded_Loss_Reserves_PMS/output/Log_Id">Log Id</operation>
                                          <operation source="field"
                                                     to="temp.s_m_Load_PMS_Ceded_Loss_Reserves_PMS/output/Task_Id">Task Id</operation>
                                          <operation source="field"
                                                     to="temp.s_m_Load_PMS_Ceded_Loss_Reserves_PMS/output/Task_Status">Task Status</operation>
                                          <operation source="field"
                                                     to="temp.s_m_Load_PMS_Ceded_Loss_Reserves_PMS/output/Success_Source_Rows">Success Source Rows</operation>
                                          <operation source="field"
                                                     to="temp.s_m_Load_PMS_Ceded_Loss_Reserves_PMS/output/Failed_Source_Rows">Failed Source Rows</operation>
                                          <operation source="field"
                                                     to="temp.s_m_Load_PMS_Ceded_Loss_Reserves_PMS/output/Success_Target_Rows">Success Target Rows</operation>
                                          <operation source="field"
                                                     to="temp.s_m_Load_PMS_Ceded_Loss_Reserves_PMS/output/Failed_Target_Rows">Failed Target Rows</operation>
                                          <operation source="field"
                                                     to="temp.s_m_Load_PMS_Ceded_Loss_Reserves_PMS/output/Start_Time">Start Time</operation>
                                          <operation source="field"
                                                     to="temp.s_m_Load_PMS_Ceded_Loss_Reserves_PMS/output/End_Time">End Time</operation>
                                          <operation source="field"
                                                     to="temp.s_m_Load_PMS_Ceded_Loss_Reserves_PMS/output/Error_Message">Error Message</operation>
                                          <operation source="field"
                                                     to="temp.s_m_Load_PMS_Ceded_Loss_Reserves_PMS/output/TotalTransErrors">Total Transformation Errors</operation>
                                          <operation source="field"
                                                     to="temp.s_m_Load_PMS_Ceded_Loss_Reserves_PMS/output/FirstErrorCode">First Error Code</operation>
                                       </serviceOutput>
                                    </service>
                                    <events>
                                       <catch faultField="temp.s_m_Load_PMS_Ceded_Loss_Reserves_PMS/fault"
                                              id="loornygf"
                                              interrupting="true"
                                              name="error"/>
                                       <catch faultField="temp.s_m_Load_PMS_Ceded_Loss_Reserves_PMS/fault"
                                              id="loornygg"
                                              interrupting="true"
                                              name="warning"/>
                                    </events>
                                 </eventContainer>
                                 <link id="loornyhg" targetId="loornyhf" type="containerLink"/>
                              </flow>
                              <flow id="loornyhj">
                                 <link id="loornyhi" targetId="loornyhf" type="containerLink"/>
                              </flow>
                              <link id="loornyhk" targetId="loornyhh" type="containerLink">
                                 <condition source="formula">
                                    <function name="starts-with-any-of">
                                       <arg name="left">{$temp.s_m_Load_CededLossOs_From_File[1]/output[1]/Task_Status}</arg>
                                       <arg name="right">1,2</arg>
                                    </function>
                                 </condition>
                              </link>
                              <link id="loornyhl" targetId="loornyhj" type="containerLink"/>
                           </container>
                           <link id="loornyh7" targetId="loornyh6" type="containerLink"/>
                        </flow>
                        <flow id="loornyha">
                           <link id="loornyh9" targetId="loornyh6" type="containerLink"/>
                        </flow>
                        <link id="loornyhb" targetId="loornyh8" type="containerLink">
                           <condition source="formula">
                              <function name="starts-with-any-of">
                                 <arg name="left">{$temp.s_m_Ceded_PMSFactLoss_ReinsuranceTransaction[1]/output[1]/Task_Status}</arg>
                                 <arg name="right">1,2</arg>
                              </function>
                           </condition>
                        </link>
                        <link id="loornyhc" targetId="loornyha" type="containerLink"/>
                     </container>
                     <link id="loornygy" targetId="loornygx" type="containerLink"/>
                  </flow>
                  <flow id="loornyh1">
                     <link id="loornyh0" targetId="loornygx" type="containerLink"/>
                  </flow>
                  <link id="loornyh2" targetId="loornygz" type="containerLink">
                     <condition source="formula">
                        <function name="starts-with-any-of">
                           <arg name="left">{$temp.s_m_Load_Ceded_LossReinsurance_Stg[1]/output[1]/Task_Status}</arg>
                           <arg name="right">1,2</arg>
                        </function>
                     </condition>
                  </link>
                  <link id="loornyh3" targetId="loornyh1" type="containerLink"/>
                  <link id="loornyho" targetId="c"/>
               </container>
               <end id="c"/>
            </flow>
            <dependencies>
               <processObject xmlns="http://schemas.active-endpoints.com/appmodules/screenflow/2011/06/avosHostEnvironment.xsd"
                              displayName="s-m-Load-CededLossOs-From-File"
                              isByCopy="true"
                              name="s-m-Load-CededLossOs-From-File">
                  <description/>
                  <tags/>
                  <detail>
                     <field label="Input Parameters"
                            name="input"
                            nullable="true"
                            required="false"
                            type="reference"/>
                     <field label="TaskProperties Parameters"
                            name="taskProperties"
                            nullable="true"
                            required="false"
                            type="reference"/>
                     <field label="Output Parameters"
                            name="output"
                            nullable="true"
                            required="false"
                            type="reference"/>
                     <field label="Fault"
                            name="fault"
                            nullable="true"
                            required="false"
                            type="reference"/>
                     <field label="Max Wait (Seconds)"
                            name="Max_Wait"
                            nullable="true"
                            required="false"
                            type="int"/>
                  </detail>
               </processObject>
               <processObject xmlns="http://schemas.active-endpoints.com/appmodules/screenflow/2011/06/avosHostEnvironment.xsd"
                              displayName="s-m-Load-PMS-Ceded-Loss-Reserves-PMS"
                              isByCopy="true"
                              name="s-m-Load-PMS-Ceded-Loss-Reserves-PMS">
                  <description/>
                  <tags/>
                  <detail>
                     <field label="Input Parameters"
                            name="input"
                            nullable="true"
                            required="false"
                            type="reference"/>
                     <field label="TaskProperties Parameters"
                            name="taskProperties"
                            nullable="true"
                            required="false"
                            type="reference"/>
                     <field label="Output Parameters"
                            name="output"
                            nullable="true"
                            required="false"
                            type="reference"/>
                     <field label="Fault"
                            name="fault"
                            nullable="true"
                            required="false"
                            type="reference"/>
                     <field label="Max Wait (Seconds)"
                            name="Max_Wait"
                            nullable="true"
                            required="false"
                            type="int"/>
                  </detail>
               </processObject>
               <processObject xmlns="http://schemas.active-endpoints.com/appmodules/screenflow/2011/06/avosHostEnvironment.xsd"
                              displayName="s-m-Load-Ceded-LossReinsurance-Stg"
                              isByCopy="true"
                              name="s-m-Load-Ceded-LossReinsurance-Stg">
                  <description/>
                  <tags/>
                  <detail>
                     <field label="Input Parameters"
                            name="input"
                            nullable="true"
                            required="false"
                            type="reference"/>
                     <field label="TaskProperties Parameters"
                            name="taskProperties"
                            nullable="true"
                            required="false"
                            type="reference"/>
                     <field label="Output Parameters"
                            name="output"
                            nullable="true"
                            required="false"
                            type="reference"/>
                     <field label="Fault"
                            name="fault"
                            nullable="true"
                            required="false"
                            type="reference"/>
                     <field label="Max Wait (Seconds)"
                            name="Max_Wait"
                            nullable="true"
                            required="false"
                            type="int"/>
                  </detail>
               </processObject>
               <processObject xmlns="http://schemas.active-endpoints.com/appmodules/screenflow/2011/06/avosHostEnvironment.xsd"
                              displayName="s-m-Ceded-PMSFactLoss-ReinsuranceTransaction"
                              isByCopy="true"
                              name="s-m-Ceded-PMSFactLoss-ReinsuranceTransaction">
                  <description/>
                  <tags/>
                  <detail>
                     <field label="Input Parameters"
                            name="input"
                            nullable="true"
                            required="false"
                            type="reference"/>
                     <field label="TaskProperties Parameters"
                            name="taskProperties"
                            nullable="true"
                            required="false"
                            type="reference"/>
                     <field label="Output Parameters"
                            name="output"
                            nullable="true"
                            required="false"
                            type="reference"/>
                     <field label="Fault"
                            name="fault"
                            nullable="true"
                            required="false"
                            type="reference"/>
                     <field label="Max Wait (Seconds)"
                            name="Max_Wait"
                            nullable="true"
                            required="false"
                            type="int"/>
                  </detail>
               </processObject>
            </dependencies>
         </taskflow>
      </types1:Entry>
      <types1:GUID>23rnKcJaYB4iiOptoliYKQ</types1:GUID>
      <types1:DisplayName>wf_m_Load_StatelineCedPaidLossHistory</types1:DisplayName>
   </types1:Item>
   <types1:CurrentServerDateTime>2024-02-12T17:55:07.493Z</types1:CurrentServerDateTime>
</aetgt:getResponse>
