{
  "objectInfo" : {
    "id" : "6YJ03RJ9iXfckXPfnU9jwZ",
    "name" : "m_update_batch_post_TableauRefresh",
    "type" : "DTEMPLATE",
    "metadata" : {
      "modelVersion" : {
        "major" : 0,
        "minor" : 0
      },
      "repoInfo" : {
        "repoHandle" : "01COEW170000000000KL"
      },
      "contextAttributes" : [ {
        "name" : "id",
        "value" : "@1"
      } ],
      "additionalInfo" : {
        "description" : "",
        "contentType" : "JSON",
        "documentState" : "VALID"
      }
    }
  },
  "dataFileExtension" : "zip",
  "updateTime" : "2024-02-28T15:41:54.349Z",
  "objectRefs" : [ ]
}