{
  "objectInfo" : {
    "id" : "9tL3WqAFG3QiD8xOZ6yD6O",
    "name" : "cdi_map_acx_data_report_bronze_load",
    "type" : "DTEMPLATE",
    "metadata" : {
      "modelVersion" : {
        "major" : 0,
        "minor" : 0
      },
      "repoInfo" : {
        "repoHandle" : "01COEW170000000001ZA"
      },
      "contextAttributes" : [ {
        "name" : "id",
        "value" : "@1"
      } ],
      "additionalInfo" : {
        "description" : "",
        "contentType" : "JSON",
        "documentState" : "VALID"
      }
    }
  },
  "dataFileExtension" : "zip",
  "updateTime" : "2025-09-17T17:56:52.034Z",
  "objectRefs" : [ ],
  "readableFileExtension" : "json",
  "readableFilePresent" : true
}